README.md
setup.py
pyRealParser/__init__.py
pyRealParser/pyRealParser.py
pyRealParser.egg-info/PKG-INFO
pyRealParser.egg-info/SOURCES.txt
pyRealParser.egg-info/dependency_links.txt
pyRealParser.egg-info/top_level.txt
test/test_tune.py