Metadata-Version: 2.1
Name: pyRealParser
Version: 0.1.0
Summary: A Python package to read songs in the iRealPro fromat.
Home-page: https://github.com/drs251/pyRealParser
Author: Daniel R. Stephan
Author-email: danrstephan@gmail.com
License: MIT
Keywords: music,chords,irealpro,jazz
Platform: Windows
Platform: Mac OS X
Platform: Linux
Classifier: Programming Language :: Python :: 3.6
Classifier: Operating System :: OS Independent
Classifier: Topic :: Artistic Software
Classifier: Topic :: Multimedia :: Sound/Audio
